{"kind":"Document","definitions":[{"kind":"ScalarTypeDefinition","name":{"kind":"Name","value":"Reference"},"description":{"kind":"StringValue","value":"References another document, used as a foreign key"},"directives":[]},{"kind":"ScalarTypeDefinition","name":{"kind":"Name","value":"JSON"},"description":{"kind":"StringValue","value":""},"directives":[]},{"kind":"ObjectTypeDefinition","interfaces":[],"directives":[],"name":{"kind":"Name","value":"SystemInfo"},"fields":[{"kind":"FieldDefinition","name":{"kind":"Name","value":"filename"},"arguments":[],"type":{"kind":"NonNullType","type":{"kind":"NamedType","name":{"kind":"Name","value":"String"}}}},{"kind":"FieldDefinition","name":{"kind":"Name","value":"title"},"arguments":[],"type":{"kind":"NamedType","name":{"kind":"Name","value":"String"}}},{"kind":"FieldDefinition","name":{"kind":"Name","value":"basename"},"arguments":[],"type":{"kind":"NonNullType","type":{"kind":"NamedType","name":{"kind":"Name","value":"String"}}}},{"kind":"FieldDefinition","name":{"kind":"Name","value":"hasReferences"},"arguments":[],"type":{"kind":"NamedType","name":{"kind":"Name","value":"Boolean"}}},{"kind":"FieldDefinition","name":{"kind":"Name","value":"breadcrumbs"},"arguments":[{"kind":"InputValueDefinition","name":{"kind":"Name","value":"excludeExtension"},"type":{"kind":"NamedType","name":{"kind":"Name","value":"Boolean"}}}],"type":{"kind":"NonNullType","type":{"kind":"ListType","type":{"kind":"NonNullType","type":{"kind":"NamedType","name":{"kind":"Name","value":"String"}}}}}},{"kind":"FieldDefinition","name":{"kind":"Name","value":"path"},"arguments":[],"type":{"kind":"NonNullType","type":{"kind":"NamedType","name":{"kind":"Name","value":"String"}}}},{"kind":"FieldDefinition","name":{"kind":"Name","value":"relativePath"},"arguments":[],"type":{"kind":"NonNullType","type":{"kind":"NamedType","name":{"kind":"Name","value":"String"}}}},{"kind":"FieldDefinition","name":{"kind":"Name","value":"extension"},"arguments":[],"type":{"kind":"NonNullType","type":{"kind":"NamedType","name":{"kind":"Name","value":"String"}}}},{"kind":"FieldDefinition","name":{"kind":"Name","value":"template"},"arguments":[],"type":{"kind":"NonNullType","type":{"kind":"NamedType","name":{"kind":"Name","value":"String"}}}},{"kind":"FieldDefinition","name":{"kind":"Name","value":"collection"},"arguments":[],"type":{"kind":"NonNullType","type":{"kind":"NamedType","name":{"kind":"Name","value":"Collection"}}}}]},{"kind":"ObjectTypeDefinition","interfaces":[],"directives":[],"name":{"kind":"Name","value":"Folder"},"fields":[{"kind":"FieldDefinition","name":{"kind":"Name","value":"name"},"arguments":[],"type":{"kind":"NonNullType","type":{"kind":"NamedType","name":{"kind":"Name","value":"String"}}}},{"kind":"FieldDefinition","name":{"kind":"Name","value":"path"},"arguments":[],"type":{"kind":"NonNullType","type":{"kind":"NamedType","name":{"kind":"Name","value":"String"}}}}]},{"kind":"ObjectTypeDefinition","interfaces":[],"directives":[],"name":{"kind":"Name","value":"PageInfo"},"fields":[{"kind":"FieldDefinition","name":{"kind":"Name","value":"hasPreviousPage"},"arguments":[],"type":{"kind":"NonNullType","type":{"kind":"NamedType","name":{"kind":"Name","value":"Boolean"}}}},{"kind":"FieldDefinition","name":{"kind":"Name","value":"hasNextPage"},"arguments":[],"type":{"kind":"NonNullType","type":{"kind":"NamedType","name":{"kind":"Name","value":"Boolean"}}}},{"kind":"FieldDefinition","name":{"kind":"Name","value":"startCursor"},"arguments":[],"type":{"kind":"NonNullType","type":{"kind":"NamedType","name":{"kind":"Name","value":"String"}}}},{"kind":"FieldDefinition","name":{"kind":"Name","value":"endCursor"},"arguments":[],"type":{"kind":"NonNullType","type":{"kind":"NamedType","name":{"kind":"Name","value":"String"}}}}]},{"kind":"InterfaceTypeDefinition","description":{"kind":"StringValue","value":""},"name":{"kind":"Name","value":"Node"},"interfaces":[],"directives":[],"fields":[{"kind":"FieldDefinition","name":{"kind":"Name","value":"id"},"arguments":[],"type":{"kind":"NonNullType","type":{"kind":"NamedType","name":{"kind":"Name","value":"ID"}}}}]},{"kind":"InterfaceTypeDefinition","description":{"kind":"StringValue","value":""},"name":{"kind":"Name","value":"Document"},"interfaces":[],"directives":[],"fields":[{"kind":"FieldDefinition","name":{"kind":"Name","value":"id"},"arguments":[],"type":{"kind":"NonNullType","type":{"kind":"NamedType","name":{"kind":"Name","value":"ID"}}}},{"kind":"FieldDefinition","name":{"kind":"Name","value":"_sys"},"arguments":[],"type":{"kind":"NamedType","name":{"kind":"Name","value":"SystemInfo"}}},{"kind":"FieldDefinition","name":{"kind":"Name","value":"_values"},"arguments":[],"type":{"kind":"NonNullType","type":{"kind":"NamedType","name":{"kind":"Name","value":"JSON"}}}}]},{"kind":"InterfaceTypeDefinition","description":{"kind":"StringValue","value":"A relay-compliant pagination connection"},"name":{"kind":"Name","value":"Connection"},"interfaces":[],"directives":[],"fields":[{"kind":"FieldDefinition","name":{"kind":"Name","value":"totalCount"},"arguments":[],"type":{"kind":"NonNullType","type":{"kind":"NamedType","name":{"kind":"Name","value":"Float"}}}},{"kind":"FieldDefinition","name":{"kind":"Name","value":"pageInfo"},"arguments":[],"type":{"kind":"NonNullType","type":{"kind":"NamedType","name":{"kind":"Name","value":"PageInfo"}}}}]},{"kind":"ObjectTypeDefinition","interfaces":[],"directives":[],"name":{"kind":"Name","value":"Query"},"fields":[{"kind":"FieldDefinition","name":{"kind":"Name","value":"getOptimizedQuery"},"arguments":[{"kind":"InputValueDefinition","name":{"kind":"Name","value":"queryString"},"type":{"kind":"NonNullType","type":{"kind":"NamedType","name":{"kind":"Name","value":"String"}}}}],"type":{"kind":"NamedType","name":{"kind":"Name","value":"String"}}},{"kind":"FieldDefinition","name":{"kind":"Name","value":"collection"},"arguments":[{"kind":"InputValueDefinition","name":{"kind":"Name","value":"collection"},"type":{"kind":"NamedType","name":{"kind":"Name","value":"String"}}}],"type":{"kind":"NonNullType","type":{"kind":"NamedType","name":{"kind":"Name","value":"Collection"}}}},{"kind":"FieldDefinition","name":{"kind":"Name","value":"collections"},"arguments":[],"type":{"kind":"NonNullType","type":{"kind":"ListType","type":{"kind":"NonNullType","type":{"kind":"NamedType","name":{"kind":"Name","value":"Collection"}}}}}},{"kind":"FieldDefinition","name":{"kind":"Name","value":"node"},"arguments":[{"kind":"InputValueDefinition","name":{"kind":"Name","value":"id"},"type":{"kind":"NamedType","name":{"kind":"Name","value":"String"}}}],"type":{"kind":"NonNullType","type":{"kind":"NamedType","name":{"kind":"Name","value":"Node"}}}},{"kind":"FieldDefinition","name":{"kind":"Name","value":"document"},"arguments":[{"kind":"InputValueDefinition","name":{"kind":"Name","value":"collection"},"type":{"kind":"NamedType","name":{"kind":"Name","value":"String"}}},{"kind":"InputValueDefinition","name":{"kind":"Name","value":"relativePath"},"type":{"kind":"NamedType","name":{"kind":"Name","value":"String"}}}],"type":{"kind":"NonNullType","type":{"kind":"NamedType","name":{"kind":"Name","value":"DocumentNode"}}}},{"kind":"FieldDefinition","name":{"kind":"Name","value":"services_es"},"arguments":[{"kind":"InputValueDefinition","name":{"kind":"Name","value":"relativePath"},"type":{"kind":"NamedType","name":{"kind":"Name","value":"String"}}}],"type":{"kind":"NonNullType","type":{"kind":"NamedType","name":{"kind":"Name","value":"Services_es"}}}},{"kind":"FieldDefinition","name":{"kind":"Name","value":"services_esConnection"},"arguments":[{"kind":"InputValueDefinition","name":{"kind":"Name","value":"before"},"type":{"kind":"NamedType","name":{"kind":"Name","value":"String"}}},{"kind":"InputValueDefinition","name":{"kind":"Name","value":"after"},"type":{"kind":"NamedType","name":{"kind":"Name","value":"String"}}},{"kind":"InputValueDefinition","name":{"kind":"Name","value":"first"},"type":{"kind":"NamedType","name":{"kind":"Name","value":"Float"}}},{"kind":"InputValueDefinition","name":{"kind":"Name","value":"last"},"type":{"kind":"NamedType","name":{"kind":"Name","value":"Float"}}},{"kind":"InputValueDefinition","name":{"kind":"Name","value":"sort"},"type":{"kind":"NamedType","name":{"kind":"Name","value":"String"}}},{"kind":"InputValueDefinition","name":{"kind":"Name","value":"filter"},"type":{"kind":"NamedType","name":{"kind":"Name","value":"Services_esFilter"}}}],"type":{"kind":"NonNullType","type":{"kind":"NamedType","name":{"kind":"Name","value":"Services_esConnection"}}}},{"kind":"FieldDefinition","name":{"kind":"Name","value":"services_ru"},"arguments":[{"kind":"InputValueDefinition","name":{"kind":"Name","value":"relativePath"},"type":{"kind":"NamedType","name":{"kind":"Name","value":"String"}}}],"type":{"kind":"NonNullType","type":{"kind":"NamedType","name":{"kind":"Name","value":"Services_ru"}}}},{"kind":"FieldDefinition","name":{"kind":"Name","value":"services_ruConnection"},"arguments":[{"kind":"InputValueDefinition","name":{"kind":"Name","value":"before"},"type":{"kind":"NamedType","name":{"kind":"Name","value":"String"}}},{"kind":"InputValueDefinition","name":{"kind":"Name","value":"after"},"type":{"kind":"NamedType","name":{"kind":"Name","value":"String"}}},{"kind":"InputValueDefinition","name":{"kind":"Name","value":"first"},"type":{"kind":"NamedType","name":{"kind":"Name","value":"Float"}}},{"kind":"InputValueDefinition","name":{"kind":"Name","value":"last"},"type":{"kind":"NamedType","name":{"kind":"Name","value":"Float"}}},{"kind":"InputValueDefinition","name":{"kind":"Name","value":"sort"},"type":{"kind":"NamedType","name":{"kind":"Name","value":"String"}}},{"kind":"InputValueDefinition","name":{"kind":"Name","value":"filter"},"type":{"kind":"NamedType","name":{"kind":"Name","value":"Services_ruFilter"}}}],"type":{"kind":"NonNullType","type":{"kind":"NamedType","name":{"kind":"Name","value":"Services_ruConnection"}}}},{"kind":"FieldDefinition","name":{"kind":"Name","value":"services_en"},"arguments":[{"kind":"InputValueDefinition","name":{"kind":"Name","value":"relativePath"},"type":{"kind":"NamedType","name":{"kind":"Name","value":"String"}}}],"type":{"kind":"NonNullType","type":{"kind":"NamedType","name":{"kind":"Name","value":"Services_en"}}}},{"kind":"FieldDefinition","name":{"kind":"Name","value":"services_enConnection"},"arguments":[{"kind":"InputValueDefinition","name":{"kind":"Name","value":"before"},"type":{"kind":"NamedType","name":{"kind":"Name","value":"String"}}},{"kind":"InputValueDefinition","name":{"kind":"Name","value":"after"},"type":{"kind":"NamedType","name":{"kind":"Name","value":"String"}}},{"kind":"InputValueDefinition","name":{"kind":"Name","value":"first"},"type":{"kind":"NamedType","name":{"kind":"Name","value":"Float"}}},{"kind":"InputValueDefinition","name":{"kind":"Name","value":"last"},"type":{"kind":"NamedType","name":{"kind":"Name","value":"Float"}}},{"kind":"InputValueDefinition","name":{"kind":"Name","value":"sort"},"type":{"kind":"NamedType","name":{"kind":"Name","value":"String"}}},{"kind":"InputValueDefinition","name":{"kind":"Name","value":"filter"},"type":{"kind":"NamedType","name":{"kind":"Name","value":"Services_enFilter"}}}],"type":{"kind":"NonNullType","type":{"kind":"NamedType","name":{"kind":"Name","value":"Services_enConnection"}}}},{"kind":"FieldDefinition","name":{"kind":"Name","value":"team_es"},"arguments":[{"kind":"InputValueDefinition","name":{"kind":"Name","value":"relativePath"},"type":{"kind":"NamedType","name":{"kind":"Name","value":"String"}}}],"type":{"kind":"NonNullType","type":{"kind":"NamedType","name":{"kind":"Name","value":"Team_es"}}}},{"kind":"FieldDefinition","name":{"kind":"Name","value":"team_esConnection"},"arguments":[{"kind":"InputValueDefinition","name":{"kind":"Name","value":"before"},"type":{"kind":"NamedType","name":{"kind":"Name","value":"String"}}},{"kind":"InputValueDefinition","name":{"kind":"Name","value":"after"},"type":{"kind":"NamedType","name":{"kind":"Name","value":"String"}}},{"kind":"InputValueDefinition","name":{"kind":"Name","value":"first"},"type":{"kind":"NamedType","name":{"kind":"Name","value":"Float"}}},{"kind":"InputValueDefinition","name":{"kind":"Name","value":"last"},"type":{"kind":"NamedType","name":{"kind":"Name","value":"Float"}}},{"kind":"InputValueDefinition","name":{"kind":"Name","value":"sort"},"type":{"kind":"NamedType","name":{"kind":"Name","value":"String"}}},{"kind":"InputValueDefinition","name":{"kind":"Name","value":"filter"},"type":{"kind":"NamedType","name":{"kind":"Name","value":"Team_esFilter"}}}],"type":{"kind":"NonNullType","type":{"kind":"NamedType","name":{"kind":"Name","value":"Team_esConnection"}}}},{"kind":"FieldDefinition","name":{"kind":"Name","value":"team_ru"},"arguments":[{"kind":"InputValueDefinition","name":{"kind":"Name","value":"relativePath"},"type":{"kind":"NamedType","name":{"kind":"Name","value":"String"}}}],"type":{"kind":"NonNullType","type":{"kind":"NamedType","name":{"kind":"Name","value":"Team_ru"}}}},{"kind":"FieldDefinition","name":{"kind":"Name","value":"team_ruConnection"},"arguments":[{"kind":"InputValueDefinition","name":{"kind":"Name","value":"before"},"type":{"kind":"NamedType","name":{"kind":"Name","value":"String"}}},{"kind":"InputValueDefinition","name":{"kind":"Name","value":"after"},"type":{"kind":"NamedType","name":{"kind":"Name","value":"String"}}},{"kind":"InputValueDefinition","name":{"kind":"Name","value":"first"},"type":{"kind":"NamedType","name":{"kind":"Name","value":"Float"}}},{"kind":"InputValueDefinition","name":{"kind":"Name","value":"last"},"type":{"kind":"NamedType","name":{"kind":"Name","value":"Float"}}},{"kind":"InputValueDefinition","name":{"kind":"Name","value":"sort"},"type":{"kind":"NamedType","name":{"kind":"Name","value":"String"}}},{"kind":"InputValueDefinition","name":{"kind":"Name","value":"filter"},"type":{"kind":"NamedType","name":{"kind":"Name","value":"Team_ruFilter"}}}],"type":{"kind":"NonNullType","type":{"kind":"NamedType","name":{"kind":"Name","value":"Team_ruConnection"}}}},{"kind":"FieldDefinition","name":{"kind":"Name","value":"team_en"},"arguments":[{"kind":"InputValueDefinition","name":{"kind":"Name","value":"relativePath"},"type":{"kind":"NamedType","name":{"kind":"Name","value":"String"}}}],"type":{"kind":"NonNullType","type":{"kind":"NamedType","name":{"kind":"Name","value":"Team_en"}}}},{"kind":"FieldDefinition","name":{"kind":"Name","value":"team_enConnection"},"arguments":[{"kind":"InputValueDefinition","name":{"kind":"Name","value":"before"},"type":{"kind":"NamedType","name":{"kind":"Name","value":"String"}}},{"kind":"InputValueDefinition","name":{"kind":"Name","value":"after"},"type":{"kind":"NamedType","name":{"kind":"Name","value":"String"}}},{"kind":"InputValueDefinition","name":{"kind":"Name","value":"first"},"type":{"kind":"NamedType","name":{"kind":"Name","value":"Float"}}},{"kind":"InputValueDefinition","name":{"kind":"Name","value":"last"},"type":{"kind":"NamedType","name":{"kind":"Name","value":"Float"}}},{"kind":"InputValueDefinition","name":{"kind":"Name","value":"sort"},"type":{"kind":"NamedType","name":{"kind":"Name","value":"String"}}},{"kind":"InputValueDefinition","name":{"kind":"Name","value":"filter"},"type":{"kind":"NamedType","name":{"kind":"Name","value":"Team_enFilter"}}}],"type":{"kind":"NonNullType","type":{"kind":"NamedType","name":{"kind":"Name","value":"Team_enConnection"}}}},{"kind":"FieldDefinition","name":{"kind":"Name","value":"pages"},"arguments":[{"kind":"InputValueDefinition","name":{"kind":"Name","value":"relativePath"},"type":{"kind":"NamedType","name":{"kind":"Name","value":"String"}}}],"type":{"kind":"NonNullType","type":{"kind":"NamedType","name":{"kind":"Name","value":"Pages"}}}},{"kind":"FieldDefinition","name":{"kind":"Name","value":"pagesConnection"},"arguments":[{"kind":"InputValueDefinition","name":{"kind":"Name","value":"before"},"type":{"kind":"NamedType","name":{"kind":"Name","value":"String"}}},{"kind":"InputValueDefinition","name":{"kind":"Name","value":"after"},"type":{"kind":"NamedType","name":{"kind":"Name","value":"String"}}},{"kind":"InputValueDefinition","name":{"kind":"Name","value":"first"},"type":{"kind":"NamedType","name":{"kind":"Name","value":"Float"}}},{"kind":"InputValueDefinition","name":{"kind":"Name","value":"last"},"type":{"kind":"NamedType","name":{"kind":"Name","value":"Float"}}},{"kind":"InputValueDefinition","name":{"kind":"Name","value":"sort"},"type":{"kind":"NamedType","name":{"kind":"Name","value":"String"}}},{"kind":"InputValueDefinition","name":{"kind":"Name","value":"filter"},"type":{"kind":"NamedType","name":{"kind":"Name","value":"PagesFilter"}}}],"type":{"kind":"NonNullType","type":{"kind":"NamedType","name":{"kind":"Name","value":"PagesConnection"}}}}]},{"kind":"InputObjectTypeDefinition","name":{"kind":"Name","value":"DocumentFilter"},"fields":[{"kind":"InputValueDefinition","name":{"kind":"Name","value":"services_es"},"type":{"kind":"NamedType","name":{"kind":"Name","value":"Services_esFilter"}}},{"kind":"InputValueDefinition","name":{"kind":"Name","value":"services_ru"},"type":{"kind":"NamedType","name":{"kind":"Name","value":"Services_ruFilter"}}},{"kind":"InputValueDefinition","name":{"kind":"Name","value":"services_en"},"type":{"kind":"NamedType","name":{"kind":"Name","value":"Services_enFilter"}}},{"kind":"InputValueDefinition","name":{"kind":"Name","value":"team_es"},"type":{"kind":"NamedType","name":{"kind":"Name","value":"Team_esFilter"}}},{"kind":"InputValueDefinition","name":{"kind":"Name","value":"team_ru"},"type":{"kind":"NamedType","name":{"kind":"Name","value":"Team_ruFilter"}}},{"kind":"InputValueDefinition","name":{"kind":"Name","value":"team_en"},"type":{"kind":"NamedType","name":{"kind":"Name","value":"Team_enFilter"}}},{"kind":"InputValueDefinition","name":{"kind":"Name","value":"pages"},"type":{"kind":"NamedType","name":{"kind":"Name","value":"PagesFilter"}}}]},{"kind":"ObjectTypeDefinition","interfaces":[],"directives":[],"name":{"kind":"Name","value":"DocumentConnectionEdges"},"fields":[{"kind":"FieldDefinition","name":{"kind":"Name","value":"cursor"},"arguments":[],"type":{"kind":"NonNullType","type":{"kind":"NamedType","name":{"kind":"Name","value":"String"}}}},{"kind":"FieldDefinition","name":{"kind":"Name","value":"node"},"arguments":[],"type":{"kind":"NamedType","name":{"kind":"Name","value":"DocumentNode"}}}]},{"kind":"ObjectTypeDefinition","interfaces":[{"kind":"NamedType","name":{"kind":"Name","value":"Connection"}}],"directives":[],"name":{"kind":"Name","value":"DocumentConnection"},"fields":[{"kind":"FieldDefinition","name":{"kind":"Name","value":"pageInfo"},"arguments":[],"type":{"kind":"NonNullType","type":{"kind":"NamedType","name":{"kind":"Name","value":"PageInfo"}}}},{"kind":"FieldDefinition","name":{"kind":"Name","value":"totalCount"},"arguments":[],"type":{"kind":"NonNullType","type":{"kind":"NamedType","name":{"kind":"Name","value":"Float"}}}},{"kind":"FieldDefinition","name":{"kind":"Name","value":"edges"},"arguments":[],"type":{"kind":"ListType","type":{"kind":"NamedType","name":{"kind":"Name","value":"DocumentConnectionEdges"}}}}]},{"kind":"ObjectTypeDefinition","interfaces":[],"directives":[],"name":{"kind":"Name","value":"Collection"},"fields":[{"kind":"FieldDefinition","name":{"kind":"Name","value":"name"},"arguments":[],"type":{"kind":"NonNullType","type":{"kind":"NamedType","name":{"kind":"Name","value":"String"}}}},{"kind":"FieldDefinition","name":{"kind":"Name","value":"slug"},"arguments":[],"type":{"kind":"NonNullType","type":{"kind":"NamedType","name":{"kind":"Name","value":"String"}}}},{"kind":"FieldDefinition","name":{"kind":"Name","value":"label"},"arguments":[],"type":{"kind":"NamedType","name":{"kind":"Name","value":"String"}}},{"kind":"FieldDefinition","name":{"kind":"Name","value":"path"},"arguments":[],"type":{"kind":"NonNullType","type":{"kind":"NamedType","name":{"kind":"Name","value":"String"}}}},{"kind":"FieldDefinition","name":{"kind":"Name","value":"format"},"arguments":[],"type":{"kind":"NamedType","name":{"kind":"Name","value":"String"}}},{"kind":"FieldDefinition","name":{"kind":"Name","value":"matches"},"arguments":[],"type":{"kind":"NamedType","name":{"kind":"Name","value":"String"}}},{"kind":"FieldDefinition","name":{"kind":"Name","value":"templates"},"arguments":[],"type":{"kind":"ListType","type":{"kind":"NamedType","name":{"kind":"Name","value":"JSON"}}}},{"kind":"FieldDefinition","name":{"kind":"Name","value":"fields"},"arguments":[],"type":{"kind":"ListType","type":{"kind":"NamedType","name":{"kind":"Name","value":"JSON"}}}},{"kind":"FieldDefinition","name":{"kind":"Name","value":"documents"},"arguments":[{"kind":"InputValueDefinition","name":{"kind":"Name","value":"before"},"type":{"kind":"NamedType","name":{"kind":"Name","value":"String"}}},{"kind":"InputValueDefinition","name":{"kind":"Name","value":"after"},"type":{"kind":"NamedType","name":{"kind":"Name","value":"String"}}},{"kind":"InputValueDefinition","name":{"kind":"Name","value":"first"},"type":{"kind":"NamedType","name":{"kind":"Name","value":"Float"}}},{"kind":"InputValueDefinition","name":{"kind":"Name","value":"last"},"type":{"kind":"NamedType","name":{"kind":"Name","value":"Float"}}},{"kind":"InputValueDefinition","name":{"kind":"Name","value":"sort"},"type":{"kind":"NamedType","name":{"kind":"Name","value":"String"}}},{"kind":"InputValueDefinition","name":{"kind":"Name","value":"filter"},"type":{"kind":"NamedType","name":{"kind":"Name","value":"DocumentFilter"}}},{"kind":"InputValueDefinition","name":{"kind":"Name","value":"folder"},"type":{"kind":"NamedType","name":{"kind":"Name","value":"String"}}}],"type":{"kind":"NonNullType","type":{"kind":"NamedType","name":{"kind":"Name","value":"DocumentConnection"}}}}]},{"kind":"UnionTypeDefinition","name":{"kind":"Name","value":"DocumentNode"},"directives":[],"types":[{"kind":"NamedType","name":{"kind":"Name","value":"Services_es"}},{"kind":"NamedType","name":{"kind":"Name","value":"Services_ru"}},{"kind":"NamedType","name":{"kind":"Name","value":"Services_en"}},{"kind":"NamedType","name":{"kind":"Name","value":"Team_es"}},{"kind":"NamedType","name":{"kind":"Name","value":"Team_ru"}},{"kind":"NamedType","name":{"kind":"Name","value":"Team_en"}},{"kind":"NamedType","name":{"kind":"Name","value":"Pages"}},{"kind":"NamedType","name":{"kind":"Name","value":"Folder"}}]},{"kind":"ObjectTypeDefinition","interfaces":[{"kind":"NamedType","name":{"kind":"Name","value":"Node"}},{"kind":"NamedType","name":{"kind":"Name","value":"Document"}}],"directives":[],"name":{"kind":"Name","value":"Services_es"},"fields":[{"kind":"FieldDefinition","name":{"kind":"Name","value":"title"},"arguments":[],"type":{"kind":"NonNullType","type":{"kind":"NamedType","name":{"kind":"Name","value":"String"}}}},{"kind":"FieldDefinition","name":{"kind":"Name","value":"price"},"arguments":[],"type":{"kind":"NamedType","name":{"kind":"Name","value":"String"}}},{"kind":"FieldDefinition","name":{"kind":"Name","value":"image"},"arguments":[],"type":{"kind":"NamedType","name":{"kind":"Name","value":"String"}}},{"kind":"FieldDefinition","name":{"kind":"Name","value":"body"},"arguments":[],"type":{"kind":"NamedType","name":{"kind":"Name","value":"JSON"}}},{"kind":"FieldDefinition","name":{"kind":"Name","value":"id"},"arguments":[],"type":{"kind":"NonNullType","type":{"kind":"NamedType","name":{"kind":"Name","value":"ID"}}}},{"kind":"FieldDefinition","name":{"kind":"Name","value":"_sys"},"arguments":[],"type":{"kind":"NonNullType","type":{"kind":"NamedType","name":{"kind":"Name","value":"SystemInfo"}}}},{"kind":"FieldDefinition","name":{"kind":"Name","value":"_values"},"arguments":[],"type":{"kind":"NonNullType","type":{"kind":"NamedType","name":{"kind":"Name","value":"JSON"}}}}]},{"kind":"InputObjectTypeDefinition","name":{"kind":"Name","value":"StringFilter"},"fields":[{"kind":"InputValueDefinition","name":{"kind":"Name","value":"startsWith"},"type":{"kind":"NamedType","name":{"kind":"Name","value":"String"}}},{"kind":"InputValueDefinition","name":{"kind":"Name","value":"eq"},"type":{"kind":"NamedType","name":{"kind":"Name","value":"String"}}},{"kind":"InputValueDefinition","name":{"kind":"Name","value":"exists"},"type":{"kind":"NamedType","name":{"kind":"Name","value":"Boolean"}}},{"kind":"InputValueDefinition","name":{"kind":"Name","value":"in"},"type":{"kind":"ListType","type":{"kind":"NamedType","name":{"kind":"Name","value":"String"}}}}]},{"kind":"InputObjectTypeDefinition","name":{"kind":"Name","value":"ImageFilter"},"fields":[{"kind":"InputValueDefinition","name":{"kind":"Name","value":"startsWith"},"type":{"kind":"NamedType","name":{"kind":"Name","value":"String"}}},{"kind":"InputValueDefinition","name":{"kind":"Name","value":"eq"},"type":{"kind":"NamedType","name":{"kind":"Name","value":"String"}}},{"kind":"InputValueDefinition","name":{"kind":"Name","value":"exists"},"type":{"kind":"NamedType","name":{"kind":"Name","value":"Boolean"}}},{"kind":"InputValueDefinition","name":{"kind":"Name","value":"in"},"type":{"kind":"ListType","type":{"kind":"NamedType","name":{"kind":"Name","value":"String"}}}}]},{"kind":"InputObjectTypeDefinition","name":{"kind":"Name","value":"RichTextFilter"},"fields":[{"kind":"InputValueDefinition","name":{"kind":"Name","value":"startsWith"},"type":{"kind":"NamedType","name":{"kind":"Name","value":"String"}}},{"kind":"InputValueDefinition","name":{"kind":"Name","value":"eq"},"type":{"kind":"NamedType","name":{"kind":"Name","value":"String"}}},{"kind":"InputValueDefinition","name":{"kind":"Name","value":"exists"},"type":{"kind":"NamedType","name":{"kind":"Name","value":"Boolean"}}}]},{"kind":"InputObjectTypeDefinition","name":{"kind":"Name","value":"Services_esFilter"},"fields":[{"kind":"InputValueDefinition","name":{"kind":"Name","value":"title"},"type":{"kind":"NamedType","name":{"kind":"Name","value":"StringFilter"}}},{"kind":"InputValueDefinition","name":{"kind":"Name","value":"price"},"type":{"kind":"NamedType","name":{"kind":"Name","value":"StringFilter"}}},{"kind":"InputValueDefinition","name":{"kind":"Name","value":"image"},"type":{"kind":"NamedType","name":{"kind":"Name","value":"ImageFilter"}}},{"kind":"InputValueDefinition","name":{"kind":"Name","value":"body"},"type":{"kind":"NamedType","name":{"kind":"Name","value":"RichTextFilter"}}}]},{"kind":"ObjectTypeDefinition","interfaces":[],"directives":[],"name":{"kind":"Name","value":"Services_esConnectionEdges"},"fields":[{"kind":"FieldDefinition","name":{"kind":"Name","value":"cursor"},"arguments":[],"type":{"kind":"NonNullType","type":{"kind":"NamedType","name":{"kind":"Name","value":"String"}}}},{"kind":"FieldDefinition","name":{"kind":"Name","value":"node"},"arguments":[],"type":{"kind":"NamedType","name":{"kind":"Name","value":"Services_es"}}}]},{"kind":"ObjectTypeDefinition","interfaces":[{"kind":"NamedType","name":{"kind":"Name","value":"Connection"}}],"directives":[],"name":{"kind":"Name","value":"Services_esConnection"},"fields":[{"kind":"FieldDefinition","name":{"kind":"Name","value":"pageInfo"},"arguments":[],"type":{"kind":"NonNullType","type":{"kind":"NamedType","name":{"kind":"Name","value":"PageInfo"}}}},{"kind":"FieldDefinition","name":{"kind":"Name","value":"totalCount"},"arguments":[],"type":{"kind":"NonNullType","type":{"kind":"NamedType","name":{"kind":"Name","value":"Float"}}}},{"kind":"FieldDefinition","name":{"kind":"Name","value":"edges"},"arguments":[],"type":{"kind":"ListType","type":{"kind":"NamedType","name":{"kind":"Name","value":"Services_esConnectionEdges"}}}}]},{"kind":"ObjectTypeDefinition","interfaces":[{"kind":"NamedType","name":{"kind":"Name","value":"Node"}},{"kind":"NamedType","name":{"kind":"Name","value":"Document"}}],"directives":[],"name":{"kind":"Name","value":"Services_ru"},"fields":[{"kind":"FieldDefinition","name":{"kind":"Name","value":"title"},"arguments":[],"type":{"kind":"NonNullType","type":{"kind":"NamedType","name":{"kind":"Name","value":"String"}}}},{"kind":"FieldDefinition","name":{"kind":"Name","value":"price"},"arguments":[],"type":{"kind":"NamedType","name":{"kind":"Name","value":"String"}}},{"kind":"FieldDefinition","name":{"kind":"Name","value":"image"},"arguments":[],"type":{"kind":"NamedType","name":{"kind":"Name","value":"String"}}},{"kind":"FieldDefinition","name":{"kind":"Name","value":"body"},"arguments":[],"type":{"kind":"NamedType","name":{"kind":"Name","value":"JSON"}}},{"kind":"FieldDefinition","name":{"kind":"Name","value":"id"},"arguments":[],"type":{"kind":"NonNullType","type":{"kind":"NamedType","name":{"kind":"Name","value":"ID"}}}},{"kind":"FieldDefinition","name":{"kind":"Name","value":"_sys"},"arguments":[],"type":{"kind":"NonNullType","type":{"kind":"NamedType","name":{"kind":"Name","value":"SystemInfo"}}}},{"kind":"FieldDefinition","name":{"kind":"Name","value":"_values"},"arguments":[],"type":{"kind":"NonNullType","type":{"kind":"NamedType","name":{"kind":"Name","value":"JSON"}}}}]},{"kind":"InputObjectTypeDefinition","name":{"kind":"Name","value":"Services_ruFilter"},"fields":[{"kind":"InputValueDefinition","name":{"kind":"Name","value":"title"},"type":{"kind":"NamedType","name":{"kind":"Name","value":"StringFilter"}}},{"kind":"InputValueDefinition","name":{"kind":"Name","value":"price"},"type":{"kind":"NamedType","name":{"kind":"Name","value":"StringFilter"}}},{"kind":"InputValueDefinition","name":{"kind":"Name","value":"image"},"type":{"kind":"NamedType","name":{"kind":"Name","value":"ImageFilter"}}},{"kind":"InputValueDefinition","name":{"kind":"Name","value":"body"},"type":{"kind":"NamedType","name":{"kind":"Name","value":"RichTextFilter"}}}]},{"kind":"ObjectTypeDefinition","interfaces":[],"directives":[],"name":{"kind":"Name","value":"Services_ruConnectionEdges"},"fields":[{"kind":"FieldDefinition","name":{"kind":"Name","value":"cursor"},"arguments":[],"type":{"kind":"NonNullType","type":{"kind":"NamedType","name":{"kind":"Name","value":"String"}}}},{"kind":"FieldDefinition","name":{"kind":"Name","value":"node"},"arguments":[],"type":{"kind":"NamedType","name":{"kind":"Name","value":"Services_ru"}}}]},{"kind":"ObjectTypeDefinition","interfaces":[{"kind":"NamedType","name":{"kind":"Name","value":"Connection"}}],"directives":[],"name":{"kind":"Name","value":"Services_ruConnection"},"fields":[{"kind":"FieldDefinition","name":{"kind":"Name","value":"pageInfo"},"arguments":[],"type":{"kind":"NonNullType","type":{"kind":"NamedType","name":{"kind":"Name","value":"PageInfo"}}}},{"kind":"FieldDefinition","name":{"kind":"Name","value":"totalCount"},"arguments":[],"type":{"kind":"NonNullType","type":{"kind":"NamedType","name":{"kind":"Name","value":"Float"}}}},{"kind":"FieldDefinition","name":{"kind":"Name","value":"edges"},"arguments":[],"type":{"kind":"ListType","type":{"kind":"NamedType","name":{"kind":"Name","value":"Services_ruConnectionEdges"}}}}]},{"kind":"ObjectTypeDefinition","interfaces":[{"kind":"NamedType","name":{"kind":"Name","value":"Node"}},{"kind":"NamedType","name":{"kind":"Name","value":"Document"}}],"directives":[],"name":{"kind":"Name","value":"Services_en"},"fields":[{"kind":"FieldDefinition","name":{"kind":"Name","value":"title"},"arguments":[],"type":{"kind":"NonNullType","type":{"kind":"NamedType","name":{"kind":"Name","value":"String"}}}},{"kind":"FieldDefinition","name":{"kind":"Name","value":"price"},"arguments":[],"type":{"kind":"NamedType","name":{"kind":"Name","value":"String"}}},{"kind":"FieldDefinition","name":{"kind":"Name","value":"image"},"arguments":[],"type":{"kind":"NamedType","name":{"kind":"Name","value":"String"}}},{"kind":"FieldDefinition","name":{"kind":"Name","value":"body"},"arguments":[],"type":{"kind":"NamedType","name":{"kind":"Name","value":"JSON"}}},{"kind":"FieldDefinition","name":{"kind":"Name","value":"id"},"arguments":[],"type":{"kind":"NonNullType","type":{"kind":"NamedType","name":{"kind":"Name","value":"ID"}}}},{"kind":"FieldDefinition","name":{"kind":"Name","value":"_sys"},"arguments":[],"type":{"kind":"NonNullType","type":{"kind":"NamedType","name":{"kind":"Name","value":"SystemInfo"}}}},{"kind":"FieldDefinition","name":{"kind":"Name","value":"_values"},"arguments":[],"type":{"kind":"NonNullType","type":{"kind":"NamedType","name":{"kind":"Name","value":"JSON"}}}}]},{"kind":"InputObjectTypeDefinition","name":{"kind":"Name","value":"Services_enFilter"},"fields":[{"kind":"InputValueDefinition","name":{"kind":"Name","value":"title"},"type":{"kind":"NamedType","name":{"kind":"Name","value":"StringFilter"}}},{"kind":"InputValueDefinition","name":{"kind":"Name","value":"price"},"type":{"kind":"NamedType","name":{"kind":"Name","value":"StringFilter"}}},{"kind":"InputValueDefinition","name":{"kind":"Name","value":"image"},"type":{"kind":"NamedType","name":{"kind":"Name","value":"ImageFilter"}}},{"kind":"InputValueDefinition","name":{"kind":"Name","value":"body"},"type":{"kind":"NamedType","name":{"kind":"Name","value":"RichTextFilter"}}}]},{"kind":"ObjectTypeDefinition","interfaces":[],"directives":[],"name":{"kind":"Name","value":"Services_enConnectionEdges"},"fields":[{"kind":"FieldDefinition","name":{"kind":"Name","value":"cursor"},"arguments":[],"type":{"kind":"NonNullType","type":{"kind":"NamedType","name":{"kind":"Name","value":"String"}}}},{"kind":"FieldDefinition","name":{"kind":"Name","value":"node"},"arguments":[],"type":{"kind":"NamedType","name":{"kind":"Name","value":"Services_en"}}}]},{"kind":"ObjectTypeDefinition","interfaces":[{"kind":"NamedType","name":{"kind":"Name","value":"Connection"}}],"directives":[],"name":{"kind":"Name","value":"Services_enConnection"},"fields":[{"kind":"FieldDefinition","name":{"kind":"Name","value":"pageInfo"},"arguments":[],"type":{"kind":"NonNullType","type":{"kind":"NamedType","name":{"kind":"Name","value":"PageInfo"}}}},{"kind":"FieldDefinition","name":{"kind":"Name","value":"totalCount"},"arguments":[],"type":{"kind":"NonNullType","type":{"kind":"NamedType","name":{"kind":"Name","value":"Float"}}}},{"kind":"FieldDefinition","name":{"kind":"Name","value":"edges"},"arguments":[],"type":{"kind":"ListType","type":{"kind":"NamedType","name":{"kind":"Name","value":"Services_enConnectionEdges"}}}}]},{"kind":"ObjectTypeDefinition","interfaces":[{"kind":"NamedType","name":{"kind":"Name","value":"Node"}},{"kind":"NamedType","name":{"kind":"Name","value":"Document"}}],"directives":[],"name":{"kind":"Name","value":"Team_es"},"fields":[{"kind":"FieldDefinition","name":{"kind":"Name","value":"name"},"arguments":[],"type":{"kind":"NonNullType","type":{"kind":"NamedType","name":{"kind":"Name","value":"String"}}}},{"kind":"FieldDefinition","name":{"kind":"Name","value":"position"},"arguments":[],"type":{"kind":"NamedType","name":{"kind":"Name","value":"String"}}},{"kind":"FieldDefinition","name":{"kind":"Name","value":"photo"},"arguments":[],"type":{"kind":"NamedType","name":{"kind":"Name","value":"String"}}},{"kind":"FieldDefinition","name":{"kind":"Name","value":"bio"},"arguments":[],"type":{"kind":"NamedType","name":{"kind":"Name","value":"String"}}},{"kind":"FieldDefinition","name":{"kind":"Name","value":"email"},"arguments":[],"type":{"kind":"NamedType","name":{"kind":"Name","value":"String"}}},{"kind":"FieldDefinition","name":{"kind":"Name","value":"phone"},"arguments":[],"type":{"kind":"NamedType","name":{"kind":"Name","value":"String"}}},{"kind":"FieldDefinition","name":{"kind":"Name","value":"id"},"arguments":[],"type":{"kind":"NonNullType","type":{"kind":"NamedType","name":{"kind":"Name","value":"ID"}}}},{"kind":"FieldDefinition","name":{"kind":"Name","value":"_sys"},"arguments":[],"type":{"kind":"NonNullType","type":{"kind":"NamedType","name":{"kind":"Name","value":"SystemInfo"}}}},{"kind":"FieldDefinition","name":{"kind":"Name","value":"_values"},"arguments":[],"type":{"kind":"NonNullType","type":{"kind":"NamedType","name":{"kind":"Name","value":"JSON"}}}}]},{"kind":"InputObjectTypeDefinition","name":{"kind":"Name","value":"Team_esFilter"},"fields":[{"kind":"InputValueDefinition","name":{"kind":"Name","value":"name"},"type":{"kind":"NamedType","name":{"kind":"Name","value":"StringFilter"}}},{"kind":"InputValueDefinition","name":{"kind":"Name","value":"position"},"type":{"kind":"NamedType","name":{"kind":"Name","value":"StringFilter"}}},{"kind":"InputValueDefinition","name":{"kind":"Name","value":"photo"},"type":{"kind":"NamedType","name":{"kind":"Name","value":"ImageFilter"}}},{"kind":"InputValueDefinition","name":{"kind":"Name","value":"bio"},"type":{"kind":"NamedType","name":{"kind":"Name","value":"StringFilter"}}},{"kind":"InputValueDefinition","name":{"kind":"Name","value":"email"},"type":{"kind":"NamedType","name":{"kind":"Name","value":"StringFilter"}}},{"kind":"InputValueDefinition","name":{"kind":"Name","value":"phone"},"type":{"kind":"NamedType","name":{"kind":"Name","value":"StringFilter"}}}]},{"kind":"ObjectTypeDefinition","interfaces":[],"directives":[],"name":{"kind":"Name","value":"Team_esConnectionEdges"},"fields":[{"kind":"FieldDefinition","name":{"kind":"Name","value":"cursor"},"arguments":[],"type":{"kind":"NonNullType","type":{"kind":"NamedType","name":{"kind":"Name","value":"String"}}}},{"kind":"FieldDefinition","name":{"kind":"Name","value":"node"},"arguments":[],"type":{"kind":"NamedType","name":{"kind":"Name","value":"Team_es"}}}]},{"kind":"ObjectTypeDefinition","interfaces":[{"kind":"NamedType","name":{"kind":"Name","value":"Connection"}}],"directives":[],"name":{"kind":"Name","value":"Team_esConnection"},"fields":[{"kind":"FieldDefinition","name":{"kind":"Name","value":"pageInfo"},"arguments":[],"type":{"kind":"NonNullType","type":{"kind":"NamedType","name":{"kind":"Name","value":"PageInfo"}}}},{"kind":"FieldDefinition","name":{"kind":"Name","value":"totalCount"},"arguments":[],"type":{"kind":"NonNullType","type":{"kind":"NamedType","name":{"kind":"Name","value":"Float"}}}},{"kind":"FieldDefinition","name":{"kind":"Name","value":"edges"},"arguments":[],"type":{"kind":"ListType","type":{"kind":"NamedType","name":{"kind":"Name","value":"Team_esConnectionEdges"}}}}]},{"kind":"ObjectTypeDefinition","interfaces":[{"kind":"NamedType","name":{"kind":"Name","value":"Node"}},{"kind":"NamedType","name":{"kind":"Name","value":"Document"}}],"directives":[],"name":{"kind":"Name","value":"Team_ru"},"fields":[{"kind":"FieldDefinition","name":{"kind":"Name","value":"name"},"arguments":[],"type":{"kind":"NonNullType","type":{"kind":"NamedType","name":{"kind":"Name","value":"String"}}}},{"kind":"FieldDefinition","name":{"kind":"Name","value":"position"},"arguments":[],"type":{"kind":"NamedType","name":{"kind":"Name","value":"String"}}},{"kind":"FieldDefinition","name":{"kind":"Name","value":"photo"},"arguments":[],"type":{"kind":"NamedType","name":{"kind":"Name","value":"String"}}},{"kind":"FieldDefinition","name":{"kind":"Name","value":"bio"},"arguments":[],"type":{"kind":"NamedType","name":{"kind":"Name","value":"String"}}},{"kind":"FieldDefinition","name":{"kind":"Name","value":"email"},"arguments":[],"type":{"kind":"NamedType","name":{"kind":"Name","value":"String"}}},{"kind":"FieldDefinition","name":{"kind":"Name","value":"phone"},"arguments":[],"type":{"kind":"NamedType","name":{"kind":"Name","value":"String"}}},{"kind":"FieldDefinition","name":{"kind":"Name","value":"id"},"arguments":[],"type":{"kind":"NonNullType","type":{"kind":"NamedType","name":{"kind":"Name","value":"ID"}}}},{"kind":"FieldDefinition","name":{"kind":"Name","value":"_sys"},"arguments":[],"type":{"kind":"NonNullType","type":{"kind":"NamedType","name":{"kind":"Name","value":"SystemInfo"}}}},{"kind":"FieldDefinition","name":{"kind":"Name","value":"_values"},"arguments":[],"type":{"kind":"NonNullType","type":{"kind":"NamedType","name":{"kind":"Name","value":"JSON"}}}}]},{"kind":"InputObjectTypeDefinition","name":{"kind":"Name","value":"Team_ruFilter"},"fields":[{"kind":"InputValueDefinition","name":{"kind":"Name","value":"name"},"type":{"kind":"NamedType","name":{"kind":"Name","value":"StringFilter"}}},{"kind":"InputValueDefinition","name":{"kind":"Name","value":"position"},"type":{"kind":"NamedType","name":{"kind":"Name","value":"StringFilter"}}},{"kind":"InputValueDefinition","name":{"kind":"Name","value":"photo"},"type":{"kind":"NamedType","name":{"kind":"Name","value":"ImageFilter"}}},{"kind":"InputValueDefinition","name":{"kind":"Name","value":"bio"},"type":{"kind":"NamedType","name":{"kind":"Name","value":"StringFilter"}}},{"kind":"InputValueDefinition","name":{"kind":"Name","value":"email"},"type":{"kind":"NamedType","name":{"kind":"Name","value":"StringFilter"}}},{"kind":"InputValueDefinition","name":{"kind":"Name","value":"phone"},"type":{"kind":"NamedType","name":{"kind":"Name","value":"StringFilter"}}}]},{"kind":"ObjectTypeDefinition","interfaces":[],"directives":[],"name":{"kind":"Name","value":"Team_ruConnectionEdges"},"fields":[{"kind":"FieldDefinition","name":{"kind":"Name","value":"cursor"},"arguments":[],"type":{"kind":"NonNullType","type":{"kind":"NamedType","name":{"kind":"Name","value":"String"}}}},{"kind":"FieldDefinition","name":{"kind":"Name","value":"node"},"arguments":[],"type":{"kind":"NamedType","name":{"kind":"Name","value":"Team_ru"}}}]},{"kind":"ObjectTypeDefinition","interfaces":[{"kind":"NamedType","name":{"kind":"Name","value":"Connection"}}],"directives":[],"name":{"kind":"Name","value":"Team_ruConnection"},"fields":[{"kind":"FieldDefinition","name":{"kind":"Name","value":"pageInfo"},"arguments":[],"type":{"kind":"NonNullType","type":{"kind":"NamedType","name":{"kind":"Name","value":"PageInfo"}}}},{"kind":"FieldDefinition","name":{"kind":"Name","value":"totalCount"},"arguments":[],"type":{"kind":"NonNullType","type":{"kind":"NamedType","name":{"kind":"Name","value":"Float"}}}},{"kind":"FieldDefinition","name":{"kind":"Name","value":"edges"},"arguments":[],"type":{"kind":"ListType","type":{"kind":"NamedType","name":{"kind":"Name","value":"Team_ruConnectionEdges"}}}}]},{"kind":"ObjectTypeDefinition","interfaces":[{"kind":"NamedType","name":{"kind":"Name","value":"Node"}},{"kind":"NamedType","name":{"kind":"Name","value":"Document"}}],"directives":[],"name":{"kind":"Name","value":"Team_en"},"fields":[{"kind":"FieldDefinition","name":{"kind":"Name","value":"name"},"arguments":[],"type":{"kind":"NonNullType","type":{"kind":"NamedType","name":{"kind":"Name","value":"String"}}}},{"kind":"FieldDefinition","name":{"kind":"Name","value":"position"},"arguments":[],"type":{"kind":"NamedType","name":{"kind":"Name","value":"String"}}},{"kind":"FieldDefinition","name":{"kind":"Name","value":"photo"},"arguments":[],"type":{"kind":"NamedType","name":{"kind":"Name","value":"String"}}},{"kind":"FieldDefinition","name":{"kind":"Name","value":"bio"},"arguments":[],"type":{"kind":"NamedType","name":{"kind":"Name","value":"String"}}},{"kind":"FieldDefinition","name":{"kind":"Name","value":"email"},"arguments":[],"type":{"kind":"NamedType","name":{"kind":"Name","value":"String"}}},{"kind":"FieldDefinition","name":{"kind":"Name","value":"phone"},"arguments":[],"type":{"kind":"NamedType","name":{"kind":"Name","value":"String"}}},{"kind":"FieldDefinition","name":{"kind":"Name","value":"id"},"arguments":[],"type":{"kind":"NonNullType","type":{"kind":"NamedType","name":{"kind":"Name","value":"ID"}}}},{"kind":"FieldDefinition","name":{"kind":"Name","value":"_sys"},"arguments":[],"type":{"kind":"NonNullType","type":{"kind":"NamedType","name":{"kind":"Name","value":"SystemInfo"}}}},{"kind":"FieldDefinition","name":{"kind":"Name","value":"_values"},"arguments":[],"type":{"kind":"NonNullType","type":{"kind":"NamedType","name":{"kind":"Name","value":"JSON"}}}}]},{"kind":"InputObjectTypeDefinition","name":{"kind":"Name","value":"Team_enFilter"},"fields":[{"kind":"InputValueDefinition","name":{"kind":"Name","value":"name"},"type":{"kind":"NamedType","name":{"kind":"Name","value":"StringFilter"}}},{"kind":"InputValueDefinition","name":{"kind":"Name","value":"position"},"type":{"kind":"NamedType","name":{"kind":"Name","value":"StringFilter"}}},{"kind":"InputValueDefinition","name":{"kind":"Name","value":"photo"},"type":{"kind":"NamedType","name":{"kind":"Name","value":"ImageFilter"}}},{"kind":"InputValueDefinition","name":{"kind":"Name","value":"bio"},"type":{"kind":"NamedType","name":{"kind":"Name","value":"StringFilter"}}},{"kind":"InputValueDefinition","name":{"kind":"Name","value":"email"},"type":{"kind":"NamedType","name":{"kind":"Name","value":"StringFilter"}}},{"kind":"InputValueDefinition","name":{"kind":"Name","value":"phone"},"type":{"kind":"NamedType","name":{"kind":"Name","value":"StringFilter"}}}]},{"kind":"ObjectTypeDefinition","interfaces":[],"directives":[],"name":{"kind":"Name","value":"Team_enConnectionEdges"},"fields":[{"kind":"FieldDefinition","name":{"kind":"Name","value":"cursor"},"arguments":[],"type":{"kind":"NonNullType","type":{"kind":"NamedType","name":{"kind":"Name","value":"String"}}}},{"kind":"FieldDefinition","name":{"kind":"Name","value":"node"},"arguments":[],"type":{"kind":"NamedType","name":{"kind":"Name","value":"Team_en"}}}]},{"kind":"ObjectTypeDefinition","interfaces":[{"kind":"NamedType","name":{"kind":"Name","value":"Connection"}}],"directives":[],"name":{"kind":"Name","value":"Team_enConnection"},"fields":[{"kind":"FieldDefinition","name":{"kind":"Name","value":"pageInfo"},"arguments":[],"type":{"kind":"NonNullType","type":{"kind":"NamedType","name":{"kind":"Name","value":"PageInfo"}}}},{"kind":"FieldDefinition","name":{"kind":"Name","value":"totalCount"},"arguments":[],"type":{"kind":"NonNullType","type":{"kind":"NamedType","name":{"kind":"Name","value":"Float"}}}},{"kind":"FieldDefinition","name":{"kind":"Name","value":"edges"},"arguments":[],"type":{"kind":"ListType","type":{"kind":"NamedType","name":{"kind":"Name","value":"Team_enConnectionEdges"}}}}]},{"kind":"ObjectTypeDefinition","interfaces":[{"kind":"NamedType","name":{"kind":"Name","value":"Node"}},{"kind":"NamedType","name":{"kind":"Name","value":"Document"}}],"directives":[],"name":{"kind":"Name","value":"Pages"},"fields":[{"kind":"FieldDefinition","name":{"kind":"Name","value":"title"},"arguments":[],"type":{"kind":"NonNullType","type":{"kind":"NamedType","name":{"kind":"Name","value":"String"}}}},{"kind":"FieldDefinition","name":{"kind":"Name","value":"language"},"arguments":[],"type":{"kind":"NonNullType","type":{"kind":"NamedType","name":{"kind":"Name","value":"String"}}}},{"kind":"FieldDefinition","name":{"kind":"Name","value":"slug"},"arguments":[],"type":{"kind":"NonNullType","type":{"kind":"NamedType","name":{"kind":"Name","value":"String"}}}},{"kind":"FieldDefinition","name":{"kind":"Name","value":"body"},"arguments":[],"type":{"kind":"NamedType","name":{"kind":"Name","value":"JSON"}}},{"kind":"FieldDefinition","name":{"kind":"Name","value":"id"},"arguments":[],"type":{"kind":"NonNullType","type":{"kind":"NamedType","name":{"kind":"Name","value":"ID"}}}},{"kind":"FieldDefinition","name":{"kind":"Name","value":"_sys"},"arguments":[],"type":{"kind":"NonNullType","type":{"kind":"NamedType","name":{"kind":"Name","value":"SystemInfo"}}}},{"kind":"FieldDefinition","name":{"kind":"Name","value":"_values"},"arguments":[],"type":{"kind":"NonNullType","type":{"kind":"NamedType","name":{"kind":"Name","value":"JSON"}}}}]},{"kind":"InputObjectTypeDefinition","name":{"kind":"Name","value":"PagesFilter"},"fields":[{"kind":"InputValueDefinition","name":{"kind":"Name","value":"title"},"type":{"kind":"NamedType","name":{"kind":"Name","value":"StringFilter"}}},{"kind":"InputValueDefinition","name":{"kind":"Name","value":"language"},"type":{"kind":"NamedType","name":{"kind":"Name","value":"StringFilter"}}},{"kind":"InputValueDefinition","name":{"kind":"Name","value":"slug"},"type":{"kind":"NamedType","name":{"kind":"Name","value":"StringFilter"}}},{"kind":"InputValueDefinition","name":{"kind":"Name","value":"body"},"type":{"kind":"NamedType","name":{"kind":"Name","value":"RichTextFilter"}}}]},{"kind":"ObjectTypeDefinition","interfaces":[],"directives":[],"name":{"kind":"Name","value":"PagesConnectionEdges"},"fields":[{"kind":"FieldDefinition","name":{"kind":"Name","value":"cursor"},"arguments":[],"type":{"kind":"NonNullType","type":{"kind":"NamedType","name":{"kind":"Name","value":"String"}}}},{"kind":"FieldDefinition","name":{"kind":"Name","value":"node"},"arguments":[],"type":{"kind":"NamedType","name":{"kind":"Name","value":"Pages"}}}]},{"kind":"ObjectTypeDefinition","interfaces":[{"kind":"NamedType","name":{"kind":"Name","value":"Connection"}}],"directives":[],"name":{"kind":"Name","value":"PagesConnection"},"fields":[{"kind":"FieldDefinition","name":{"kind":"Name","value":"pageInfo"},"arguments":[],"type":{"kind":"NonNullType","type":{"kind":"NamedType","name":{"kind":"Name","value":"PageInfo"}}}},{"kind":"FieldDefinition","name":{"kind":"Name","value":"totalCount"},"arguments":[],"type":{"kind":"NonNullType","type":{"kind":"NamedType","name":{"kind":"Name","value":"Float"}}}},{"kind":"FieldDefinition","name":{"kind":"Name","value":"edges"},"arguments":[],"type":{"kind":"ListType","type":{"kind":"NamedType","name":{"kind":"Name","value":"PagesConnectionEdges"}}}}]},{"kind":"ObjectTypeDefinition","interfaces":[],"directives":[],"name":{"kind":"Name","value":"Mutation"},"fields":[{"kind":"FieldDefinition","name":{"kind":"Name","value":"addPendingDocument"},"arguments":[{"kind":"InputValueDefinition","name":{"kind":"Name","value":"collection"},"type":{"kind":"NonNullType","type":{"kind":"NamedType","name":{"kind":"Name","value":"String"}}}},{"kind":"InputValueDefinition","name":{"kind":"Name","value":"relativePath"},"type":{"kind":"NonNullType","type":{"kind":"NamedType","name":{"kind":"Name","value":"String"}}}},{"kind":"InputValueDefinition","name":{"kind":"Name","value":"template"},"type":{"kind":"NamedType","name":{"kind":"Name","value":"String"}}}],"type":{"kind":"NonNullType","type":{"kind":"NamedType","name":{"kind":"Name","value":"DocumentNode"}}}},{"kind":"FieldDefinition","name":{"kind":"Name","value":"updateDocument"},"arguments":[{"kind":"InputValueDefinition","name":{"kind":"Name","value":"collection"},"type":{"kind":"NamedType","name":{"kind":"Name","value":"String"}}},{"kind":"InputValueDefinition","name":{"kind":"Name","value":"relativePath"},"type":{"kind":"NonNullType","type":{"kind":"NamedType","name":{"kind":"Name","value":"String"}}}},{"kind":"InputValueDefinition","name":{"kind":"Name","value":"params"},"type":{"kind":"NonNullType","type":{"kind":"NamedType","name":{"kind":"Name","value":"DocumentUpdateMutation"}}}}],"type":{"kind":"NonNullType","type":{"kind":"NamedType","name":{"kind":"Name","value":"DocumentNode"}}}},{"kind":"FieldDefinition","name":{"kind":"Name","value":"deleteDocument"},"arguments":[{"kind":"InputValueDefinition","name":{"kind":"Name","value":"collection"},"type":{"kind":"NamedType","name":{"kind":"Name","value":"String"}}},{"kind":"InputValueDefinition","name":{"kind":"Name","value":"relativePath"},"type":{"kind":"NonNullType","type":{"kind":"NamedType","name":{"kind":"Name","value":"String"}}}}],"type":{"kind":"NonNullType","type":{"kind":"NamedType","name":{"kind":"Name","value":"DocumentNode"}}}},{"kind":"FieldDefinition","name":{"kind":"Name","value":"createDocument"},"arguments":[{"kind":"InputValueDefinition","name":{"kind":"Name","value":"collection"},"type":{"kind":"NamedType","name":{"kind":"Name","value":"String"}}},{"kind":"InputValueDefinition","name":{"kind":"Name","value":"relativePath"},"type":{"kind":"NonNullType","type":{"kind":"NamedType","name":{"kind":"Name","value":"String"}}}},{"kind":"InputValueDefinition","name":{"kind":"Name","value":"params"},"type":{"kind":"NonNullType","type":{"kind":"NamedType","name":{"kind":"Name","value":"DocumentMutation"}}}}],"type":{"kind":"NonNullType","type":{"kind":"NamedType","name":{"kind":"Name","value":"DocumentNode"}}}},{"kind":"FieldDefinition","name":{"kind":"Name","value":"createFolder"},"arguments":[{"kind":"InputValueDefinition","name":{"kind":"Name","value":"collection"},"type":{"kind":"NamedType","name":{"kind":"Name","value":"String"}}},{"kind":"InputValueDefinition","name":{"kind":"Name","value":"relativePath"},"type":{"kind":"NonNullType","type":{"kind":"NamedType","name":{"kind":"Name","value":"String"}}}}],"type":{"kind":"NonNullType","type":{"kind":"NamedType","name":{"kind":"Name","value":"DocumentNode"}}}},{"kind":"FieldDefinition","name":{"kind":"Name","value":"updateServices_es"},"arguments":[{"kind":"InputValueDefinition","name":{"kind":"Name","value":"relativePath"},"type":{"kind":"NonNullType","type":{"kind":"NamedType","name":{"kind":"Name","value":"String"}}}},{"kind":"InputValueDefinition","name":{"kind":"Name","value":"params"},"type":{"kind":"NonNullType","type":{"kind":"NamedType","name":{"kind":"Name","value":"Services_esMutation"}}}}],"type":{"kind":"NonNullType","type":{"kind":"NamedType","name":{"kind":"Name","value":"Services_es"}}}},{"kind":"FieldDefinition","name":{"kind":"Name","value":"createServices_es"},"arguments":[{"kind":"InputValueDefinition","name":{"kind":"Name","value":"relativePath"},"type":{"kind":"NonNullType","type":{"kind":"NamedType","name":{"kind":"Name","value":"String"}}}},{"kind":"InputValueDefinition","name":{"kind":"Name","value":"params"},"type":{"kind":"NonNullType","type":{"kind":"NamedType","name":{"kind":"Name","value":"Services_esMutation"}}}}],"type":{"kind":"NonNullType","type":{"kind":"NamedType","name":{"kind":"Name","value":"Services_es"}}}},{"kind":"FieldDefinition","name":{"kind":"Name","value":"updateServices_ru"},"arguments":[{"kind":"InputValueDefinition","name":{"kind":"Name","value":"relativePath"},"type":{"kind":"NonNullType","type":{"kind":"NamedType","name":{"kind":"Name","value":"String"}}}},{"kind":"InputValueDefinition","name":{"kind":"Name","value":"params"},"type":{"kind":"NonNullType","type":{"kind":"NamedType","name":{"kind":"Name","value":"Services_ruMutation"}}}}],"type":{"kind":"NonNullType","type":{"kind":"NamedType","name":{"kind":"Name","value":"Services_ru"}}}},{"kind":"FieldDefinition","name":{"kind":"Name","value":"createServices_ru"},"arguments":[{"kind":"InputValueDefinition","name":{"kind":"Name","value":"relativePath"},"type":{"kind":"NonNullType","type":{"kind":"NamedType","name":{"kind":"Name","value":"String"}}}},{"kind":"InputValueDefinition","name":{"kind":"Name","value":"params"},"type":{"kind":"NonNullType","type":{"kind":"NamedType","name":{"kind":"Name","value":"Services_ruMutation"}}}}],"type":{"kind":"NonNullType","type":{"kind":"NamedType","name":{"kind":"Name","value":"Services_ru"}}}},{"kind":"FieldDefinition","name":{"kind":"Name","value":"updateServices_en"},"arguments":[{"kind":"InputValueDefinition","name":{"kind":"Name","value":"relativePath"},"type":{"kind":"NonNullType","type":{"kind":"NamedType","name":{"kind":"Name","value":"String"}}}},{"kind":"InputValueDefinition","name":{"kind":"Name","value":"params"},"type":{"kind":"NonNullType","type":{"kind":"NamedType","name":{"kind":"Name","value":"Services_enMutation"}}}}],"type":{"kind":"NonNullType","type":{"kind":"NamedType","name":{"kind":"Name","value":"Services_en"}}}},{"kind":"FieldDefinition","name":{"kind":"Name","value":"createServices_en"},"arguments":[{"kind":"InputValueDefinition","name":{"kind":"Name","value":"relativePath"},"type":{"kind":"NonNullType","type":{"kind":"NamedType","name":{"kind":"Name","value":"String"}}}},{"kind":"InputValueDefinition","name":{"kind":"Name","value":"params"},"type":{"kind":"NonNullType","type":{"kind":"NamedType","name":{"kind":"Name","value":"Services_enMutation"}}}}],"type":{"kind":"NonNullType","type":{"kind":"NamedType","name":{"kind":"Name","value":"Services_en"}}}},{"kind":"FieldDefinition","name":{"kind":"Name","value":"updateTeam_es"},"arguments":[{"kind":"InputValueDefinition","name":{"kind":"Name","value":"relativePath"},"type":{"kind":"NonNullType","type":{"kind":"NamedType","name":{"kind":"Name","value":"String"}}}},{"kind":"InputValueDefinition","name":{"kind":"Name","value":"params"},"type":{"kind":"NonNullType","type":{"kind":"NamedType","name":{"kind":"Name","value":"Team_esMutation"}}}}],"type":{"kind":"NonNullType","type":{"kind":"NamedType","name":{"kind":"Name","value":"Team_es"}}}},{"kind":"FieldDefinition","name":{"kind":"Name","value":"createTeam_es"},"arguments":[{"kind":"InputValueDefinition","name":{"kind":"Name","value":"relativePath"},"type":{"kind":"NonNullType","type":{"kind":"NamedType","name":{"kind":"Name","value":"String"}}}},{"kind":"InputValueDefinition","name":{"kind":"Name","value":"params"},"type":{"kind":"NonNullType","type":{"kind":"NamedType","name":{"kind":"Name","value":"Team_esMutation"}}}}],"type":{"kind":"NonNullType","type":{"kind":"NamedType","name":{"kind":"Name","value":"Team_es"}}}},{"kind":"FieldDefinition","name":{"kind":"Name","value":"updateTeam_ru"},"arguments":[{"kind":"InputValueDefinition","name":{"kind":"Name","value":"relativePath"},"type":{"kind":"NonNullType","type":{"kind":"NamedType","name":{"kind":"Name","value":"String"}}}},{"kind":"InputValueDefinition","name":{"kind":"Name","value":"params"},"type":{"kind":"NonNullType","type":{"kind":"NamedType","name":{"kind":"Name","value":"Team_ruMutation"}}}}],"type":{"kind":"NonNullType","type":{"kind":"NamedType","name":{"kind":"Name","value":"Team_ru"}}}},{"kind":"FieldDefinition","name":{"kind":"Name","value":"createTeam_ru"},"arguments":[{"kind":"InputValueDefinition","name":{"kind":"Name","value":"relativePath"},"type":{"kind":"NonNullType","type":{"kind":"NamedType","name":{"kind":"Name","value":"String"}}}},{"kind":"InputValueDefinition","name":{"kind":"Name","value":"params"},"type":{"kind":"NonNullType","type":{"kind":"NamedType","name":{"kind":"Name","value":"Team_ruMutation"}}}}],"type":{"kind":"NonNullType","type":{"kind":"NamedType","name":{"kind":"Name","value":"Team_ru"}}}},{"kind":"FieldDefinition","name":{"kind":"Name","value":"updateTeam_en"},"arguments":[{"kind":"InputValueDefinition","name":{"kind":"Name","value":"relativePath"},"type":{"kind":"NonNullType","type":{"kind":"NamedType","name":{"kind":"Name","value":"String"}}}},{"kind":"InputValueDefinition","name":{"kind":"Name","value":"params"},"type":{"kind":"NonNullType","type":{"kind":"NamedType","name":{"kind":"Name","value":"Team_enMutation"}}}}],"type":{"kind":"NonNullType","type":{"kind":"NamedType","name":{"kind":"Name","value":"Team_en"}}}},{"kind":"FieldDefinition","name":{"kind":"Name","value":"createTeam_en"},"arguments":[{"kind":"InputValueDefinition","name":{"kind":"Name","value":"relativePath"},"type":{"kind":"NonNullType","type":{"kind":"NamedType","name":{"kind":"Name","value":"String"}}}},{"kind":"InputValueDefinition","name":{"kind":"Name","value":"params"},"type":{"kind":"NonNullType","type":{"kind":"NamedType","name":{"kind":"Name","value":"Team_enMutation"}}}}],"type":{"kind":"NonNullType","type":{"kind":"NamedType","name":{"kind":"Name","value":"Team_en"}}}},{"kind":"FieldDefinition","name":{"kind":"Name","value":"updatePages"},"arguments":[{"kind":"InputValueDefinition","name":{"kind":"Name","value":"relativePath"},"type":{"kind":"NonNullType","type":{"kind":"NamedType","name":{"kind":"Name","value":"String"}}}},{"kind":"InputValueDefinition","name":{"kind":"Name","value":"params"},"type":{"kind":"NonNullType","type":{"kind":"NamedType","name":{"kind":"Name","value":"PagesMutation"}}}}],"type":{"kind":"NonNullType","type":{"kind":"NamedType","name":{"kind":"Name","value":"Pages"}}}},{"kind":"FieldDefinition","name":{"kind":"Name","value":"createPages"},"arguments":[{"kind":"InputValueDefinition","name":{"kind":"Name","value":"relativePath"},"type":{"kind":"NonNullType","type":{"kind":"NamedType","name":{"kind":"Name","value":"String"}}}},{"kind":"InputValueDefinition","name":{"kind":"Name","value":"params"},"type":{"kind":"NonNullType","type":{"kind":"NamedType","name":{"kind":"Name","value":"PagesMutation"}}}}],"type":{"kind":"NonNullType","type":{"kind":"NamedType","name":{"kind":"Name","value":"Pages"}}}}]},{"kind":"InputObjectTypeDefinition","name":{"kind":"Name","value":"DocumentUpdateMutation"},"fields":[{"kind":"InputValueDefinition","name":{"kind":"Name","value":"services_es"},"type":{"kind":"NamedType","name":{"kind":"Name","value":"Services_esMutation"}}},{"kind":"InputValueDefinition","name":{"kind":"Name","value":"services_ru"},"type":{"kind":"NamedType","name":{"kind":"Name","value":"Services_ruMutation"}}},{"kind":"InputValueDefinition","name":{"kind":"Name","value":"services_en"},"type":{"kind":"NamedType","name":{"kind":"Name","value":"Services_enMutation"}}},{"kind":"InputValueDefinition","name":{"kind":"Name","value":"team_es"},"type":{"kind":"NamedType","name":{"kind":"Name","value":"Team_esMutation"}}},{"kind":"InputValueDefinition","name":{"kind":"Name","value":"team_ru"},"type":{"kind":"NamedType","name":{"kind":"Name","value":"Team_ruMutation"}}},{"kind":"InputValueDefinition","name":{"kind":"Name","value":"team_en"},"type":{"kind":"NamedType","name":{"kind":"Name","value":"Team_enMutation"}}},{"kind":"InputValueDefinition","name":{"kind":"Name","value":"pages"},"type":{"kind":"NamedType","name":{"kind":"Name","value":"PagesMutation"}}},{"kind":"InputValueDefinition","name":{"kind":"Name","value":"relativePath"},"type":{"kind":"NamedType","name":{"kind":"Name","value":"String"}}}]},{"kind":"InputObjectTypeDefinition","name":{"kind":"Name","value":"DocumentMutation"},"fields":[{"kind":"InputValueDefinition","name":{"kind":"Name","value":"services_es"},"type":{"kind":"NamedType","name":{"kind":"Name","value":"Services_esMutation"}}},{"kind":"InputValueDefinition","name":{"kind":"Name","value":"services_ru"},"type":{"kind":"NamedType","name":{"kind":"Name","value":"Services_ruMutation"}}},{"kind":"InputValueDefinition","name":{"kind":"Name","value":"services_en"},"type":{"kind":"NamedType","name":{"kind":"Name","value":"Services_enMutation"}}},{"kind":"InputValueDefinition","name":{"kind":"Name","value":"team_es"},"type":{"kind":"NamedType","name":{"kind":"Name","value":"Team_esMutation"}}},{"kind":"InputValueDefinition","name":{"kind":"Name","value":"team_ru"},"type":{"kind":"NamedType","name":{"kind":"Name","value":"Team_ruMutation"}}},{"kind":"InputValueDefinition","name":{"kind":"Name","value":"team_en"},"type":{"kind":"NamedType","name":{"kind":"Name","value":"Team_enMutation"}}},{"kind":"InputValueDefinition","name":{"kind":"Name","value":"pages"},"type":{"kind":"NamedType","name":{"kind":"Name","value":"PagesMutation"}}}]},{"kind":"InputObjectTypeDefinition","name":{"kind":"Name","value":"Services_esMutation"},"fields":[{"kind":"InputValueDefinition","name":{"kind":"Name","value":"title"},"type":{"kind":"NamedType","name":{"kind":"Name","value":"String"}}},{"kind":"InputValueDefinition","name":{"kind":"Name","value":"price"},"type":{"kind":"NamedType","name":{"kind":"Name","value":"String"}}},{"kind":"InputValueDefinition","name":{"kind":"Name","value":"image"},"type":{"kind":"NamedType","name":{"kind":"Name","value":"String"}}},{"kind":"InputValueDefinition","name":{"kind":"Name","value":"body"},"type":{"kind":"NamedType","name":{"kind":"Name","value":"JSON"}}}]},{"kind":"InputObjectTypeDefinition","name":{"kind":"Name","value":"Services_ruMutation"},"fields":[{"kind":"InputValueDefinition","name":{"kind":"Name","value":"title"},"type":{"kind":"NamedType","name":{"kind":"Name","value":"String"}}},{"kind":"InputValueDefinition","name":{"kind":"Name","value":"price"},"type":{"kind":"NamedType","name":{"kind":"Name","value":"String"}}},{"kind":"InputValueDefinition","name":{"kind":"Name","value":"image"},"type":{"kind":"NamedType","name":{"kind":"Name","value":"String"}}},{"kind":"InputValueDefinition","name":{"kind":"Name","value":"body"},"type":{"kind":"NamedType","name":{"kind":"Name","value":"JSON"}}}]},{"kind":"InputObjectTypeDefinition","name":{"kind":"Name","value":"Services_enMutation"},"fields":[{"kind":"InputValueDefinition","name":{"kind":"Name","value":"title"},"type":{"kind":"NamedType","name":{"kind":"Name","value":"String"}}},{"kind":"InputValueDefinition","name":{"kind":"Name","value":"price"},"type":{"kind":"NamedType","name":{"kind":"Name","value":"String"}}},{"kind":"InputValueDefinition","name":{"kind":"Name","value":"image"},"type":{"kind":"NamedType","name":{"kind":"Name","value":"String"}}},{"kind":"InputValueDefinition","name":{"kind":"Name","value":"body"},"type":{"kind":"NamedType","name":{"kind":"Name","value":"JSON"}}}]},{"kind":"InputObjectTypeDefinition","name":{"kind":"Name","value":"Team_esMutation"},"fields":[{"kind":"InputValueDefinition","name":{"kind":"Name","value":"name"},"type":{"kind":"NamedType","name":{"kind":"Name","value":"String"}}},{"kind":"InputValueDefinition","name":{"kind":"Name","value":"position"},"type":{"kind":"NamedType","name":{"kind":"Name","value":"String"}}},{"kind":"InputValueDefinition","name":{"kind":"Name","value":"photo"},"type":{"kind":"NamedType","name":{"kind":"Name","value":"String"}}},{"kind":"InputValueDefinition","name":{"kind":"Name","value":"bio"},"type":{"kind":"NamedType","name":{"kind":"Name","value":"String"}}},{"kind":"InputValueDefinition","name":{"kind":"Name","value":"email"},"type":{"kind":"NamedType","name":{"kind":"Name","value":"String"}}},{"kind":"InputValueDefinition","name":{"kind":"Name","value":"phone"},"type":{"kind":"NamedType","name":{"kind":"Name","value":"String"}}}]},{"kind":"InputObjectTypeDefinition","name":{"kind":"Name","value":"Team_ruMutation"},"fields":[{"kind":"InputValueDefinition","name":{"kind":"Name","value":"name"},"type":{"kind":"NamedType","name":{"kind":"Name","value":"String"}}},{"kind":"InputValueDefinition","name":{"kind":"Name","value":"position"},"type":{"kind":"NamedType","name":{"kind":"Name","value":"String"}}},{"kind":"InputValueDefinition","name":{"kind":"Name","value":"photo"},"type":{"kind":"NamedType","name":{"kind":"Name","value":"String"}}},{"kind":"InputValueDefinition","name":{"kind":"Name","value":"bio"},"type":{"kind":"NamedType","name":{"kind":"Name","value":"String"}}},{"kind":"InputValueDefinition","name":{"kind":"Name","value":"email"},"type":{"kind":"NamedType","name":{"kind":"Name","value":"String"}}},{"kind":"InputValueDefinition","name":{"kind":"Name","value":"phone"},"type":{"kind":"NamedType","name":{"kind":"Name","value":"String"}}}]},{"kind":"InputObjectTypeDefinition","name":{"kind":"Name","value":"Team_enMutation"},"fields":[{"kind":"InputValueDefinition","name":{"kind":"Name","value":"name"},"type":{"kind":"NamedType","name":{"kind":"Name","value":"String"}}},{"kind":"InputValueDefinition","name":{"kind":"Name","value":"position"},"type":{"kind":"NamedType","name":{"kind":"Name","value":"String"}}},{"kind":"InputValueDefinition","name":{"kind":"Name","value":"photo"},"type":{"kind":"NamedType","name":{"kind":"Name","value":"String"}}},{"kind":"InputValueDefinition","name":{"kind":"Name","value":"bio"},"type":{"kind":"NamedType","name":{"kind":"Name","value":"String"}}},{"kind":"InputValueDefinition","name":{"kind":"Name","value":"email"},"type":{"kind":"NamedType","name":{"kind":"Name","value":"String"}}},{"kind":"InputValueDefinition","name":{"kind":"Name","value":"phone"},"type":{"kind":"NamedType","name":{"kind":"Name","value":"String"}}}]},{"kind":"InputObjectTypeDefinition","name":{"kind":"Name","value":"PagesMutation"},"fields":[{"kind":"InputValueDefinition","name":{"kind":"Name","value":"title"},"type":{"kind":"NamedType","name":{"kind":"Name","value":"String"}}},{"kind":"InputValueDefinition","name":{"kind":"Name","value":"language"},"type":{"kind":"NamedType","name":{"kind":"Name","value":"String"}}},{"kind":"InputValueDefinition","name":{"kind":"Name","value":"slug"},"type":{"kind":"NamedType","name":{"kind":"Name","value":"String"}}},{"kind":"InputValueDefinition","name":{"kind":"Name","value":"body"},"type":{"kind":"NamedType","name":{"kind":"Name","value":"JSON"}}}]}]}